cni/__init__.py
cni/box.py
cni/constants.py
cni/dlo.py
cni/dlogen.py
cni/ellipse.py
cni/font.py
cni/geo.py
cni/grouping.py
cni/instance.py
cni/layer.py
cni/location.py
cni/namemapper.py
cni/net.py
cni/numeric.py
cni/orientation.py
cni/paramarray.py
cni/path.py
cni/pathstyle.py
cni/physicalComponent.py
cni/physicalrule.py
cni/pin.py
cni/point.py
cni/pointlist.py
cni/polygon.py
cni/rect.py
cni/sg13_tech.py
cni/sg13g2_tech.json
cni/shape.py
cni/shapefilter.py
cni/signaltype.py
cni/tech.py
cni/term.py
cni/termtype.py
cni/text.py
cni/transform.py
cni/ulist.py
ihp/__init__.py
ihp/config.py
ihp/import_pdk.py
ihp/layers.yaml
ihp/tech.py
ihp/cells/__init__.py
ihp/cells/antennas.py
ihp/cells/bipolar.py
ihp/cells/bjt_transistors.py
ihp/cells/bondpads.py
ihp/cells/capacitors.py
ihp/cells/containers.py
ihp/cells/fixed.py
ihp/cells/inductors.py
ihp/cells/passives.py
ihp/cells/primitives.py
ihp/cells/resistors.py
ihp/cells/text.py
ihp/cells/transistors.py
ihp/cells/via_stacks.py
ihp/cells/waveguides.py
ihp/cells2/__init__.py
ihp/cells2/antennas.py
ihp/cells2/bjt_transistors.py
ihp/cells2/bondpads.py
ihp/cells2/capacitors.py
ihp/cells2/containers.py
ihp/cells2/fixed.py
ihp/cells2/inductors.py
ihp/cells2/mos_transistors.py
ihp/cells2/passives.py
ihp/cells2/resistors.py
ihp/cells2/text.py
ihp/cells2/utils.py
ihp/cells2/via_stacks.py
ihp/cells2/waveguides.py
ihp/cells2/ihp_pycell/NoFillerStack_code.py
ihp/cells2/ihp_pycell/SVaricap_code.py
ihp/cells2/ihp_pycell/__init__.py
ihp/cells2/ihp_pycell/bondpad_code.py
ihp/cells2/ihp_pycell/cmim_code.py
ihp/cells2/ihp_pycell/dantenna_code.py
ihp/cells2/ihp_pycell/dpantenna_code.py
ihp/cells2/ihp_pycell/esd_code.py
ihp/cells2/ihp_pycell/geometry.py
ihp/cells2/ihp_pycell/inductor2_code.py
ihp/cells2/ihp_pycell/inductor3_code.py
ihp/cells2/ihp_pycell/inductors_code.py
ihp/cells2/ihp_pycell/nmosHV_code.py
ihp/cells2/ihp_pycell/nmos_code.py
ihp/cells2/ihp_pycell/npn13G2L_code.py
ihp/cells2/ihp_pycell/npn13G2V_code.py
ihp_gdsfactory-0.1.4.dist-info/licenses/LICENSE
ihp_gdsfactory-0.1.4.dist-info/METADATA
ihp_gdsfactory-0.1.4.dist-info/WHEEL
ihp_gdsfactory-0.1.4.dist-info/top_level.txt
ihp_gdsfactory-0.1.4.dist-info/RECORD
