Metadata-Version: 2.4
Name: ihp-gdsfactory
Version: 0.1.4
Summary: IHP pdk
Author-email: gdsfactory <contact@gdsfactory.com>
License:                                  Apache License
Keywords: python
Classifier: Programming Language :: Python :: 3.11
Classifier: Programming Language :: Python :: 3.12
Classifier: Programming Language :: Python :: 3.13
Requires-Python: <3.14,>=3.11
License-File: LICENSE
Requires-Dist: gdsfactory<9.33,>=9.24
Requires-Dist: gplugins[sax]~=2.0.0
Requires-Dist: doroutes>=0.2.0
Requires-Dist: vlsir>=7.0.0
Requires-Dist: vlsirtools>=7.0.0
Provides-Extra: dev
Requires-Dist: pytest; extra == "dev"
Requires-Dist: pytest-cov; extra == "dev"
Requires-Dist: pytest_regressions; extra == "dev"
Requires-Dist: jsondiff; extra == "dev"
Requires-Dist: pytest-github-actions-annotate-failures; extra == "dev"
Requires-Dist: pre-commit; extra == "dev"
Provides-Extra: docs
Requires-Dist: autodoc_pydantic; extra == "docs"
Requires-Dist: jupytext; extra == "docs"
Requires-Dist: jupyter-book==1.0.3; extra == "docs"
Dynamic: license-file
